{"content": {"RANKED_FLEX_SR": {"content": {"winrate": {"value": 0.4860335195530726, "type": "numeric", "name": "Winrate"}, "leagueName": {"value": "Evelynn's Marauders", "type": "string", "name": "League name"}, "wins": {"value": 87, "type": "numeric", "name": "Wins"}, "leaguePoints": {"value": 94, "type": "numeric", "name": "League points"}, "losses": {"value": 92, "type": "numeric", "name": "Losses"}, "games": {"value": 179, "type": "numeric", "name": "Games"}, "rank": {"value": "II", "type": "string", "name": "Rank"}, "tier": {"value": "PLATINUM", "type": "string", "name": "Tier"}, "image": {"value": "http://canisback.com/img/lol/platinum.png", "type": "img", "name": "Rank image"}}, "type": "block", "name": "Ranked Flex 5x5"}, "RANKED_SOLO_5x5": {"content": {"winrate": {"value": 0.48626373626373626, "type": "numeric", "name": "Winrate"}, "leagueName": {"value": "Vayne's Elementalists", "type": "string", "name": "League name"}, "wins": {"value": 177, "type": "numeric", "name": "Wins"}, "leaguePoints": {"value": 55, "type": "numeric", "name": "League points"}, "losses": {"value": 187, "type": "numeric", "name": "Losses"}, "games": {"value": 364, "type": "numeric", "name": "Games"}, "rank": {"value": "I", "type": "string", "name": "Rank"}, "tier": {"value": "PLATINUM", "type": "string", "name": "Tier"}, "image": {"value": "http://canisback.com/img/lol/platinum.png", "type": "img", "name": "Rank image"}}, "type": "block", "name": "Ranked Solo 5x5"}, "RANKED_FLEX_TT": {"content": {"winrate": {"value": 0.0, "type": "numeric", "name": "Winrate"}, "leagueName": {"value": "", "type": "string", "name": "League name"}, "wins": {"value": 0.0, "type": "numeric", "name": "Wins"}, "leaguePoints": {"value": 0.0, "type": "numeric", "name": "League points"}, "losses": {"value": 0.0, "type": "numeric", "name": "Losses"}, "games": {"value": 0.0, "type": "numeric", "name": "Games"}, "rank": {"value": "", "type": "string", "name": "Rank"}, "tier": {"value": "Unranked", "type": "string", "name": "Tier"}, "image": {"value": "http://canisback.com/img/lol/unranked.png", "type": "img", "name": "Rank image"}}, "type": "block", "name": "Ranked Flex 3x3"}}, "type": "block", "name": "League"}